ci/Jenkinsfile_schedview.conda
docs/Makefile
docs/api.rst
docs/architecture.rst
docs/conf.py
docs/documenteer.toml
docs/examples.rst
docs/index.rst
docs/installation.rst
docs/introduction.rst
docs/playwright_testing.rst
docs/prenight_sim_generation.rst
docs/reports.rst
docs/tutorials.rst
docs/usage.rst
docs/figures/prenight.png
docs/figures/scheduler_dashboard.png
notebooks/architecture.ipynb
notebooks/custom_plot.json
notebooks/footprint_polygons.ipynb
notebooks/introduction.ipynb
notebooks/make_test_schedulers.ipynb
notebooks/mpcorb_sample_big.dat
notebooks/mpcorb_sample_sdss.dat
notebooks/prenight.ipynb
notebooks/prenight_matplotlib_extension.ipynb
notebooks/prenight_multielement_extension.ipynb
notebooks/prenight_rewardplot.ipynb
notebooks/scheduler.ipynb
schedview/__init__.py
schedview/clientsite.py
schedview/dayobs.py
schedview/param.py
schedview/reports.py
schedview/sphere.py
schedview/util.py
schedview/version.py
schedview/app/__init__.py
schedview/app/obs_version_at_time.py
schedview/app/prenight_inventory.py
schedview/app/scheduler_config_at_time.py
schedview/app/start.py
schedview/app/sched_maps/main.py
schedview/app/sched_maps/sched_maps.py
schedview/app/sched_maps/templates/index.html
schedview/app/scheduler_dashboard/__init__.py
schedview/app/scheduler_dashboard/constants.py
schedview/app/scheduler_dashboard/lfa_scheduler_snapshot_dashboard.py
schedview/app/scheduler_dashboard/restricted_scheduler_snapshot_dashboard.py
schedview/app/scheduler_dashboard/scheduler_dashboard_app.py
schedview/app/scheduler_dashboard/unrestricted_scheduler_snapshot_dashboard.py
schedview/app/scheduler_dashboard/utils.py
schedview/app/scheduler_dashboard/assets/lsst_white_logo.png
schedview/collect/__init__.py
schedview/collect/auth.py
schedview/collect/consdb.py
schedview/collect/efd.py
schedview/collect/footprint.py
schedview/collect/logdb.py
schedview/collect/metrics.py
schedview/collect/multisim.py
schedview/collect/nightreport.py
schedview/collect/opsim.py
schedview-0.21.0.dist-info/licenses/LICENSE
schedview-0.21.0.dist-info/METADATA
schedview-0.21.0.dist-info/WHEEL
schedview-0.21.0.dist-info/entry_points.txt
schedview-0.21.0.dist-info/top_level.txt
schedview-0.21.0.dist-info/RECORD
