Metadata-Version: 2.4
Name: schedview
Version: 0.21.0
Summary: Tools for visualization of Rubin Observatory's scheduler status, strategy and progress on LSST.
Author: Eric Neilsen, Lynne Jones, Eman Ali, Alice Serene
Project-URL: documentation, https://schedview.lsst.io
Project-URL: repository, https://github.com/lsst/schedview
Classifier: Intended Audience :: Science/Research
Classifier: Operating System :: OS Independent
Classifier: Programming Language :: Python :: 3
Classifier: Programming Language :: Python :: 3.11
Classifier: Topic :: Scientific/Engineering :: Astronomy
License-File: LICENSE
Requires-Dist: astropy>=5.3
Requires-Dist: colorcet
Requires-Dist: bokeh>=3.1.1
Requires-Dist: healpy
Requires-Dist: holoviews
Requires-Dist: hvplot
Requires-Dist: lsst-efd-client
Requires-Dist: lsst-resources
Requires-Dist: matplotlib
Requires-Dist: numpy
Requires-Dist: pandas
Requires-Dist: panel>=1.1.0
Requires-Dist: param
Requires-Dist: psycopg2
Requires-Dist: pytz
Requires-Dist: skyproj
Requires-Dist: tabulate
Requires-Dist: rubin-scheduler>=3.18.0
Requires-Dist: rubin-sim>=2.6.0
Requires-Dist: uranography>=1.4.1
Provides-Extra: test
Requires-Dist: pytest; extra == "test"
Requires-Dist: black; extra == "test"
Requires-Dist: isort; extra == "test"
Requires-Dist: ruff; extra == "test"
Requires-Dist: pytest-cov; extra == "test"
Requires-Dist: geckodriver; extra == "test"
Requires-Dist: playwright; extra == "test"
Requires-Dist: pre-commit; extra == "test"
Provides-Extra: dev
Requires-Dist: documenteer[guide]; extra == "dev"
Dynamic: license-file
